{"stats":{"minecraft:dropped":{"deathrium_collection:the_real_forge_hammer":2,"minecraft:tuff":23,"deathrium_collection:bedrock_shard":81,"minecraft:red_sand":1},"minecraft:used":{"minecraft:red_sand":3,"minecraft:villager_spawn_egg":27,"minecraft:torch":12,"deathrium_collection:obsidian_weakness":4,"minecraft:anvil":1,"minecraft:cobblestone":20,"minecraft:crafting_table":2,"minecraft:blast_furnace":2,"minecraft:furnace":1,"deathrium_collection:the_real_forge_hammer":776,"minecraft:smithing_table":1,"minecraft:netherite_pickaxe":4,"deathrium_collection:unfinished_forge_hammer":30},"minecraft:killed":{"minecraft:villager":33},"minecraft:mined":{"minecraft:white_terracotta":12,"minecraft:deepslate_redstone_ore":1,"minecraft:yellow_terracotta":6,"deathrium_collection:obsidian_weakness":1,"minecraft:cactus":1,"minecraft:red_terracotta":3,"minecraft:tuff":21,"minecraft:iron_ore":2,"minecraft:orange_terracotta":47,"minecraft:crafting_table":1,"minecraft:light_gray_terracotta":22,"minecraft:granite":4,"minecraft:blast_furnace":1,"minecraft:red_sand":31,"minecraft:dead_bush":3,"minecraft:copper_ore":1,"minecraft:terracotta":45,"minecraft:stone":75,"minecraft:diorite":15,"minecraft:deepslate":72},"minecraft:picked_up":{"minecraft:crafting_table":1,"minecraft:stick":10,"minecraft:raw_iron":2,"minecraft:tuff":23,"deathrium_collection:bedrock_shard":399,"minecraft:blast_furnace":1,"minecraft:diorite":18,"minecraft:redstone":27,"minecraft:orange_terracotta":153,"minecraft:light_gray_terracotta":2,"deathrium_collection:obsidian_weakness":1,"minecraft:cactus":1,"minecraft:red_sand":24,"minecraft:cobbled_deepslate":139,"minecraft:granite":5,"minecraft:yellow_terracotta":9,"minecraft:white_terracotta":4,"minecraft:terracotta":8,"deathrium_collection:the_real_forge_hammer":2,"minecraft:coal":47,"minecraft:cobblestone":103},"minecraft:custom":{"minecraft:sprint_one_cm":51461,"minecraft:interact_with_furnace":9,"minecraft:walk_one_cm":46849,"minecraft:mob_kills":33,"minecraft:interact_with_anvil":9,"minecraft:drop":6,"minecraft:damage_dealt":6590,"minecraft:interact_with_crafting_table":7,"minecraft:fly_one_cm":142247,"minecraft:crouch_one_cm":137,"minecraft:play_time":36447,"minecraft:sneak_time":350,"minecraft:walk_under_water_one_cm":1692,"minecraft:jump":588,"minecraft:interact_with_blast_furnace":7,"minecraft:leave_game":11,"minecraft:time_since_death":36447,"minecraft:walk_on_water_one_cm":269,"minecraft:total_world_time":41220,"minecraft:fall_one_cm":22556,"minecraft:damage_taken":250,"minecraft:interact_with_smithing_table":2,"minecraft:time_since_rest":36447},"minecraft:crafted":{"deathrium_collection:the_real_forge_hammer":1,"deathrium_collection:unfinished_forge_hammer":1,"deathrium_collection:obsidian_weakness":4,"deathrium_collection:pink_coated_bone":2,"deathrium_collection:putrid_gem":32,"deathrium_collection:pink_furnace_core":1,"deathrium_collection:oxidized_alloy":128,"deathrium_collection:pink_iron_ingot":128,"minecraft:air":0}},"DataVersion":2975}